README.md
setup.cfg
setup.py
explo/__init__.py
explo/__main__.py
explo/color.py
explo/connection.py
explo/core.py
explo/exceptions.py
explo/util.py
explo.egg-info/PKG-INFO
explo.egg-info/SOURCES.txt
explo.egg-info/dependency_links.txt
explo.egg-info/entry_points.txt
explo.egg-info/requires.txt
explo.egg-info/top_level.txt
explo/modules/__init__.py
explo/modules/http.py
explo/modules/http_header.py
explo/modules/report.py
explo/modules/sqli_blind.py