Metadata-Version: 1.0
Name: explo
Version: 0.2.2
Summary: Test web based vulnerabilities from a .yaml file
Home-page: https://github.com/dtag-dev-sec/explo
Author: Robin Verton
Author-email: hello@robinverton.de
License: UNKNOWN
Platform: any
